{
  "m_Version": 12,
  "DisplayName": "#STR_EXPANSION_MARKET_CATEGORY_SUBMACHINE_GUNS",
  "Icon": "Deliver",
  "Color": "FBFCFEFF",
  "InitStockPercent": 75.0,
  "IsExchange": 0,
  "Items": [
    {
      "ClassName": "expansion_mp5",
      "MaxPriceThreshold": 3800,
      "MinPriceThreshold": 3100,
      "SellPricePercent": -1.0,
      "MaxStockThreshold": 100,
      "MinStockThreshold": 1,
      "QuantityPercent": -1,
      "SpawnAttachments": [
        "mag_mp5_30rnd"
      ],
      "Variants": []
    },
    {
      "ClassName": "expansion_mp5sd",
      "MaxPriceThreshold": 4000,
      "MinPriceThreshold": 3600,
      "SellPricePercent": -1.0,
      "MaxStockThreshold": 100,
      "MinStockThreshold": 1,
      "QuantityPercent": -1,
      "SpawnAttachments": [
        "mag_mp5_30rnd"
      ],
      "Variants": []
    },
    {
      "ClassName": "expansion_mp7",
      "MaxPriceThreshold": 3200,
      "MinPriceThreshold": 2400,
      "SellPricePercent": -1.0,
      "MaxStockThreshold": 100,
      "MinStockThreshold": 1,
      "QuantityPercent": -1,
      "SpawnAttachments": [
        "mag_expansion_mp7_40rnd"
      ],
      "Variants": []
    },
    {
      "ClassName": "expansion_mpx",
      "MaxPriceThreshold": 3200,
      "MinPriceThreshold": 3000,
      "SellPricePercent": -1.0,
      "MaxStockThreshold": 100,
      "MinStockThreshold": 1,
      "QuantityPercent": -1,
      "SpawnAttachments": [
        "mag_expansion_mpx_50rnd"
      ],
      "Variants": []
    },
    {
      "ClassName": "mp5k",
      "MaxPriceThreshold": 3800,
      "MinPriceThreshold": 3300,
      "SellPricePercent": -1.0,
      "MaxStockThreshold": 100,
      "MinStockThreshold": 1,
      "QuantityPercent": -1,
      "SpawnAttachments": [
        "mp5k_stockbttstck",
        "mp5_plastichndgrd",
        "mag_mp5_30rnd"
      ],
      "Variants": []
    },
    {
      "ClassName": "ump45",
      "MaxPriceThreshold": 3000,
      "MinPriceThreshold": 2800,
      "SellPricePercent": -1.0,
      "MaxStockThreshold": 100,
      "MinStockThreshold": 1,
      "QuantityPercent": -1,
      "SpawnAttachments": [
        "mag_ump_25rnd"
      ],
      "Variants": []
    }
  ]
}